<system modnum="3" tasknum="79" bandwidth="98.0713" mesnum="11">
    <modules>
        <pc>3</pc>
        <pc>4</pc>
        <pc>2</pc>
    </modules>
    <tasks>
        <task period="40" time="4" left="0" right="40" messize="37" />
        <task period="80" time="4" left="0" right="80" messize="55" />
        <task period="80" time="4" left="0" right="80" messize="57" />
        <task period="160" time="4" left="0" right="160" messize="56" />
        <task period="320" time="4" left="0" right="320" messize="65" />
        <task period="320" time="4" left="0" right="320" messize="70" />
        <task period="640" time="4" left="0" right="640" messize="41" />
        <task period="640" time="4" left="0" right="640" messize="74" />
        <task period="1280" time="4" left="0" right="1280" messize="48" />
        <task period="80" time="4" left="0" right="80" messize="35" />
        <task period="80" time="4" left="0" right="80" messize="65" />
        <task period="80" time="4" left="0" right="80" messize="74" />
        <task period="160" time="4" left="0" right="160" messize="59" />
        <task period="320" time="4" left="0" right="320" messize="28" />
        <task period="320" time="4" left="0" right="320" messize="49" />
        <task period="640" time="4" left="0" right="640" messize="27" />
        <task period="1280" time="4" left="0" right="1280" messize="59" />
        <task period="40" time="4" left="0" right="40" messize="53" />
        <task period="160" time="4" left="0" right="160" messize="63" />
        <task period="160" time="4" left="0" right="160" messize="15" />
        <task period="320" time="4" left="0" right="320" messize="44" />
        <task period="320" time="4" left="0" right="320" messize="41" />
        <task period="640" time="4" left="0" right="640" messize="28" />
        <task period="1280" time="4" left="0" right="1280" messize="31" />
        <task period="40" time="4" left="0" right="40" messize="88" />
        <task period="80" time="4" left="0" right="80" messize="33" />
        <task period="80" time="4" left="0" right="80" messize="62" />
        <task period="320" time="5" left="0" right="320" messize="65" />
        <task period="320" time="5" left="0" right="320" messize="37" />
        <task period="640" time="5" left="0" right="640" messize="67" />
        <task period="40" time="5" left="0" right="40" messize="68" />
        <task period="80" time="5" left="0" right="80" messize="55" />
        <task period="80" time="5" left="0" right="80" messize="26" />
        <task period="160" time="5" left="0" right="160" messize="47" />
        <task period="160" time="5" left="0" right="160" messize="71" />
        <task period="640" time="5" left="0" right="640" messize="25" />
        <task period="640" time="5" left="0" right="640" messize="45" />
        <task period="80" time="5" left="0" right="80" messize="55" />
        <task period="80" time="5" left="0" right="80" messize="78" />
        <task period="160" time="5" left="0" right="160" messize="53" />
        <task period="160" time="5" left="0" right="160" messize="55" />
        <task period="320" time="5" left="0" right="320" messize="64" />
        <task period="320" time="5" left="0" right="320" messize="56" />
        <task period="1280" time="4" left="0" right="1280" messize="43" />
        <task period="80" time="4" left="0" right="80" messize="32" />
        <task period="80" time="4" left="0" right="80" messize="81" />
        <task period="160" time="4" left="0" right="160" messize="63" />
        <task period="160" time="4" left="0" right="160" messize="68" />
        <task period="320" time="4" left="0" right="320" messize="69" />
        <task period="320" time="4" left="0" right="320" messize="53" />
        <task period="640" time="4" left="0" right="640" messize="66" />
        <task period="640" time="4" left="0" right="640" messize="68" />
        <task period="2560" time="4" left="0" right="2560" messize="70" />
        <task period="80" time="4" left="0" right="80" messize="38" />
        <task period="80" time="4" left="0" right="80" messize="30" />
        <task period="160" time="4" left="0" right="160" messize="35" />
        <task period="160" time="4" left="0" right="160" messize="25" />
        <task period="320" time="4" left="0" right="320" messize="48" />
        <task period="320" time="4" left="0" right="320" messize="42" />
        <task period="640" time="4" left="0" right="640" messize="42" />
        <task period="640" time="4" left="0" right="640" messize="28" />
        <task period="1280" time="4" left="0" right="1280" messize="49" />
        <task period="80" time="4" left="0" right="80" messize="45" />
        <task period="80" time="4" left="0" right="80" messize="71" />
        <task period="160" time="4" left="0" right="160" messize="37" />
        <task period="160" time="4" left="0" right="160" messize="45" />
        <task period="320" time="4" left="0" right="320" messize="59" />
        <task period="320" time="4" left="0" right="320" messize="38" />
        <task period="640" time="4" left="0" right="640" messize="14" />
        <task period="640" time="4" left="0" right="640" messize="59" />
        <task period="1280" time="4" left="0" right="1280" messize="38" />
        <task period="80" time="5" left="0" right="80" messize="45" />
        <task period="80" time="5" left="0" right="80" messize="63" />
        <task period="160" time="5" left="0" right="160" messize="25" />
        <task period="320" time="5" left="0" right="320" messize="39" />
        <task period="320" time="5" left="0" right="320" messize="42" />
        <task period="640" time="5" left="0" right="640" messize="56" />
        <task period="640" time="5" left="0" right="640" messize="34" />
        <task period="1280" time="5" left="0" right="1280" messize="53" />
    </tasks>
    <messages>
        <mes src="40" dest="39" size="69" />
        <mes src="10" dest="25" size="54" />
        <mes src="19" dest="55" size="43" />
        <mes src="24" dest="17" size="75" />
        <mes src="36" dest="29" size="33" />
        <mes src="29" dest="68" size="40" />
        <mes src="37" dest="31" size="63" />
        <mes src="49" dest="5" size="75" />
        <mes src="47" dest="33" size="80" />
        <mes src="65" dest="73" size="71" />
        <mes src="69" dest="6" size="59" />
    </messages>
</system>
