<system modnum="6" tasknum="77" bandwidth="45.193" mesnum="3">
    <modules>
        <pc>3</pc>
        <pc>1</pc>
        <pc>1</pc>
        <pc>4</pc>
        <pc>5</pc>
        <pc>2</pc>
    </modules>
    <tasks>
        <task period="32" time="6" left="0" right="32" messize="89" />
        <task period="32" time="6" left="0" right="32" messize="57" />
        <task period="32" time="6" left="0" right="32" messize="47" />
        <task period="64" time="6" left="0" right="64" messize="41" />
        <task period="64" time="6" left="0" right="64" messize="43" />
        <task period="64" time="5" left="0" right="64" messize="75" />
        <task period="64" time="5" left="0" right="64" messize="67" />
        <task period="64" time="5" left="0" right="64" messize="60" />
        <task period="32" time="5" left="0" right="32" messize="82" />
        <task period="32" time="5" left="0" right="32" messize="66" />
        <task period="32" time="5" left="0" right="32" messize="40" />
        <task period="128" time="4" left="0" right="128" messize="44" />
        <task period="32" time="4" left="0" right="32" messize="59" />
        <task period="32" time="4" left="0" right="32" messize="79" />
        <task period="32" time="4" left="0" right="32" messize="45" />
        <task period="64" time="4" left="0" right="64" messize="64" />
        <task period="64" time="4" left="0" right="64" messize="35" />
        <task period="64" time="4" left="0" right="64" messize="53" />
        <task period="256" time="4" left="0" right="256" messize="47" />
        <task period="32" time="4" left="0" right="32" messize="42" />
        <task period="32" time="4" left="0" right="32" messize="33" />
        <task period="32" time="4" left="0" right="32" messize="49" />
        <task period="64" time="4" left="0" right="64" messize="42" />
        <task period="64" time="4" left="0" right="64" messize="16" />
        <task period="64" time="4" left="0" right="64" messize="67" />
        <task period="128" time="4" left="0" right="128" messize="54" />
        <task period="32" time="5" left="0" right="32" messize="23" />
        <task period="32" time="5" left="0" right="32" messize="20" />
        <task period="64" time="5" left="0" right="64" messize="78" />
        <task period="64" time="5" left="0" right="64" messize="36" />
        <task period="64" time="5" left="0" right="64" messize="55" />
        <task period="256" time="5" left="0" right="256" messize="41" />
        <task period="64" time="6" left="0" right="64" messize="80" />
        <task period="64" time="6" left="0" right="64" messize="54" />
        <task period="256" time="6" left="0" right="256" messize="62" />
        <task period="32" time="6" left="0" right="32" messize="48" />
        <task period="32" time="6" left="0" right="32" messize="68" />
        <task period="32" time="8" left="0" right="32" messize="30" />
        <task period="32" time="8" left="0" right="32" messize="72" />
        <task period="64" time="8" left="0" right="64" messize="62" />
        <task period="64" time="8" left="0" right="64" messize="73" />
        <task period="32" time="8" left="0" right="32" messize="24" />
        <task period="32" time="8" left="0" right="32" messize="52" />
        <task period="64" time="8" left="0" right="64" messize="44" />
        <task period="64" time="8" left="0" right="64" messize="55" />
        <task period="32" time="8" left="0" right="32" messize="49" />
        <task period="32" time="8" left="0" right="32" messize="54" />
        <task period="64" time="8" left="0" right="64" messize="41" />
        <task period="64" time="8" left="0" right="64" messize="36" />
        <task period="64" time="8" left="0" right="64" messize="32" />
        <task period="64" time="8" left="0" right="64" messize="56" />
        <task period="32" time="8" left="0" right="32" messize="53" />
        <task period="32" time="8" left="0" right="32" messize="42" />
        <task period="32" time="8" left="0" right="32" messize="51" />
        <task period="32" time="8" left="0" right="32" messize="67" />
        <task period="64" time="8" left="0" right="64" messize="39" />
        <task period="64" time="8" left="0" right="64" messize="58" />
        <task period="32" time="8" left="0" right="32" messize="38" />
        <task period="32" time="8" left="0" right="32" messize="61" />
        <task period="64" time="8" left="0" right="64" messize="51" />
        <task period="64" time="8" left="0" right="64" messize="47" />
        <task period="32" time="8" left="0" right="32" messize="22" />
        <task period="32" time="8" left="0" right="32" messize="78" />
        <task period="64" time="8" left="0" right="64" messize="59" />
        <task period="64" time="8" left="0" right="64" messize="64" />
        <task period="64" time="8" left="0" right="64" messize="36" />
        <task period="64" time="8" left="0" right="64" messize="41" />
        <task period="32" time="8" left="0" right="32" messize="59" />
        <task period="32" time="8" left="0" right="32" messize="50" />
        <task period="32" time="8" left="0" right="32" messize="45" />
        <task period="32" time="8" left="0" right="32" messize="73" />
        <task period="64" time="8" left="0" right="64" messize="79" />
        <task period="64" time="8" left="0" right="64" messize="31" />
        <task period="32" time="8" left="0" right="32" messize="98" />
        <task period="32" time="8" left="0" right="32" messize="51" />
        <task period="64" time="8" left="0" right="64" messize="27" />
        <task period="64" time="8" left="0" right="64" messize="30" />
    </tasks>
    <messages>
        <mes src="0" dest="35" size="52" />
        <mes src="5" dest="76" size="43" />
        <mes src="22" dest="48" size="64" />
    </messages>
</system>
